skunectar/__init__.py
skunectar/skuclient.py
skunectar-1.0.0.dist-info/METADATA
skunectar-1.0.0.dist-info/WHEEL
skunectar-1.0.0.dist-info/top_level.txt
skunectar-1.0.0.dist-info/RECORD
