Metadata-Version: 2.1
Name: skunectar
Version: 1.0.0
Summary: An open-source Skupos library for connecting to various databases.
Home-page: UNKNOWN
Author: Neil Jelmert Jorgensen
Author-email: njorgensen@skupos.com
License: MIT
Platform: UNKNOWN
Classifier: Development Status :: 3 - Alpha
Classifier: Intended Audience :: Developers
Classifier: Topic :: Software Development :: Build Tools
Classifier: License :: OSI Approved :: MIT License
Classifier: Programming Language :: Python :: 3.6
Classifier: Programming Language :: Python :: 3.7
Classifier: Programming Language :: Python :: 3.8
Requires-Python: >=3.6, <=3.8
Requires-Dist: python-dotenv
Requires-Dist: pandas (==1.0.1)
Requires-Dist: snowflake-connector-python[pandas]
